encoding_information/__init__.py
encoding_information/_version.py
encoding_information/bsccm_utils.py
encoding_information/error_bars.py
encoding_information/gpu_utils.py
encoding_information/image_utils.py
encoding_information/information_estimation.py
encoding_information/plot_utils.py
encoding_information/models/gaussian_process.py
encoding_information/models/image_distribution_models.py
encoding_information/models/pixel_cnn.py
encoding_information-0.1.1.dist-info/LICENSE
encoding_information-0.1.1.dist-info/WHEEL
encoding_information-0.1.1.dist-info/METADATA
encoding_information-0.1.1.dist-info/RECORD
