Metadata-Version: 2.1
Name: encoding_information
Version: 0.1.1
Summary: Estimating encoded information
Author: Henry Pinkard
Classifier: License :: OSI Approved :: BSD License
Requires-Dist: numpy
Project-URL: Home, https://github.com/Waller-Lab/EncodingInformation
